aicp_helper/__init__.py
aicp_helper/const.py
aicp_helper/helper.py
aicp_helper/aicp_config/__init__.py
aicp_helper-1.0.9.dist-info/METADATA
aicp_helper-1.0.9.dist-info/WHEEL
aicp_helper-1.0.9.dist-info/top_level.txt
aicp_helper-1.0.9.dist-info/RECORD
