Metadata-Version: 2.4
Name: aicp-helper
Version: 1.0.9
Summary: AICP Helper SDK - AI Cloud Platform 工具库
Author: AICP Team
Author-email: aicp-team@coreshub.cn
Maintainer: syw
Maintainer-email: syw@coreshub.cn
Requires-Python: >=3.9
Requires-Dist: redis~=5.0.1
Requires-Dist: pydash~=8.0.3
Requires-Dist: httpx
Dynamic: author
Dynamic: author-email
Dynamic: description
Dynamic: description-content-type
Dynamic: maintainer
Dynamic: maintainer-email
Dynamic: requires-dist
Dynamic: requires-python
Dynamic: summary
